{
  "_meta": {
    "version": "2.0.0",
    "description": "Merchant catalogs for Canon Engine"
  },
  "default": {
    "items": [
      {"name": "Health Potion", "price": 25, "rarity": "common", "type": "consumable"},
      {"name": "Bread Loaf", "price": 2, "rarity": "dirt", "type": "food"},
      {"name": "Torch", "price": 3, "rarity": "dirt", "type": "tool"},
      {"name": "Hempen Rope (50ft)", "price": 10, "rarity": "common", "type": "tool"},
      {"name": "Antidote", "price": 15, "rarity": "common", "type": "consumable"},
      {"name": "Bandages", "price": 5, "rarity": "dirt", "type": "consumable"},
      {"name": "Waterskin", "price": 4, "rarity": "dirt", "type": "tool"},
      {"name": "Rations (3 days)", "price": 12, "rarity": "dirt", "type": "food"},
      {"name": "Lantern", "price": 15, "rarity": "common", "type": "tool"},
      {"name": "Tent", "price": 30, "rarity": "common", "type": "tool"}
    ]
  },
  "blacksmith": {
    "items": [
      {"name": "Iron Sword", "price": 50, "rarity": "common", "type": "weapon"},
      {"name": "Steel Dagger", "price": 30, "rarity": "common", "type": "weapon"},
      {"name": "Chain Mail", "price": 120, "rarity": "uncommon", "type": "armor"},
      {"name": "Iron Shield", "price": 45, "rarity": "common", "type": "armor"},
      {"name": "Battle Axe", "price": 65, "rarity": "uncommon", "type": "weapon"},
      {"name": "Steel Helm", "price": 40, "rarity": "common", "type": "armor"},
      {"name": "Iron Gauntlets", "price": 25, "rarity": "common", "type": "armor"},
      {"name": "Whetstone", "price": 3, "rarity": "dirt", "type": "tool"},
      {"name": "Shielding Ring", "price": 200, "rarity": "rare", "type": "accessory"},
      {"name": "Enchanted Blade", "price": 500, "rarity": "epic", "type": "weapon"}
    ]
  },
  "healer": {
    "items": [
      {"name": "Greater Health Potion", "price": 75, "rarity": "uncommon", "type": "consumable"},
      {"name": "Mana Elixir", "price": 60, "rarity": "uncommon", "type": "consumable"},
      {"name": "Cure Disease Tonic", "price": 40, "rarity": "common", "type": "consumable"},
      {"name": "Phoenix Down", "price": 500, "rarity": "rare", "type": "consumable"},
      {"name": "Herbal Poultice", "price": 20, "rarity": "common", "type": "consumable"},
      {"name": "Antidote+", "price": 35, "rarity": "uncommon", "type": "consumable"},
      {"name": "Stamina Draught", "price": 45, "rarity": "common", "type": "consumable"},
      {"name": "Holy Water", "price": 25, "rarity": "common", "type": "consumable"}
    ]
  }
}
